foggy/__init__.py
foggy/foggy.py
foggy/mainloop.py
foggy-1.0.dist-info/METADATA
foggy-1.0.dist-info/WHEEL
foggy-1.0.dist-info/top_level.txt
foggy-1.0.dist-info/RECORD
