Metadata-Version: 2.1
Name: foggy
Version: 1.0
Summary: foggy is a python package for using a CNN to predict fog at airports
Home-page: https://gitlab.com/tamara.pletzer/foggy
Author: Tamara Pletzer
Author-email: tamara.pletzer@gmail.com
License: MIT
Platform: UNKNOWN
Classifier: Development Status :: 4 - Beta
Classifier: License :: OSI Approved :: MIT License
Classifier: Programming Language :: Python
Classifier: Programming Language :: Python :: 3.5
Classifier: Programming Language :: Python :: 3.6
Classifier: Topic :: Software Development :: Libraries
Classifier: Topic :: Software Development :: Libraries :: Python Modules
Classifier: Intended Audience :: Developers
Requires-Python: >=3.7
Requires-Dist: cfgrib
Requires-Dist: pandas
Requires-Dist: numpy
Requires-Dist: pytest-shutil
Requires-Dist: tensorflow
Requires-Dist: matplotlib
Requires-Dist: cartopy
Requires-Dist: scipy
Requires-Dist: imblearn
Requires-Dist: scikit-learn
